zstring/__init__.py
zstring/classes.py
zstring/constants.py
zstring/functions.py
zstring-1.0.4.dist-info/METADATA
zstring-1.0.4.dist-info/WHEEL
zstring-1.0.4.dist-info/top_level.txt
zstring-1.0.4.dist-info/RECORD
