Metadata-Version: 2.1
Name: zstring
Version: 1.0.4
Summary: The successor for the string module. Part of the zen standard library.
Author: Schkimansky
Author-email: <ahmadchawla1432@gmail.com>
Keywords: python,string,zen
Classifier: Development Status :: 5 - Production/Stable
Classifier: Intended Audience :: Developers
Classifier: Programming Language :: Python :: 3
Classifier: Operating System :: OS Independent
